nonebot_plugin_bird_lg-0.1.0.dist-info/METADATA
nonebot_plugin_bird_lg-0.1.0.dist-info/WHEEL
nonebot_plugin_bird_lg-0.1.0.dist-info/licenses/LICENSE
nonebot_plugin_bird_lg/__init__.py
nonebot_plugin_bird_lg/__main__.py
nonebot_plugin_bird_lg/config.py
nonebot_plugin_bird_lg/utils.py
nonebot_plugin_bird_lg-0.1.0.dist-info/RECORD
