Metadata-Version: 2.1
Name: nonebot-plugin-bird-lg
Version: 0.1.0
Summary: Use command to get bird status in QQ.
Home-page: https://github.com/lgc-NB2Dev/nonebot-plugin-bird-lg
Author-Email: student_2333 <lgc2333@126.com>, XieXiLin <support@xiexilin.com>
License: MIT
Project-URL: Homepage, https://github.com/lgc-NB2Dev/nonebot-plugin-bird-lg
Requires-Python: <4.0,>=3.8
Requires-Dist: nonebot2>=2.0.0
Requires-Dist: nonebot-adapter-onebot>=2.2.0
Requires-Dist: pydantic<2,>=1.10.4
Requires-Dist: httpx>=0.25.0
Requires-Dist: pandas>=2.0.3
Requires-Dist: matplotlib>=3.7.3
